tree_sitter/__init__.py
tree_sitter/__init__.pyi
tree_sitter/_binding.cpython-313-darwin.so
tree_sitter/py.typed
tree_sitter_language_version_15-0.25.0.dist-info/licenses/LICENSE
tree_sitter_language_version_15-0.25.0.dist-info/METADATA
tree_sitter_language_version_15-0.25.0.dist-info/WHEEL
tree_sitter_language_version_15-0.25.0.dist-info/top_level.txt
tree_sitter_language_version_15-0.25.0.dist-info/RECORD
