Metadata-Version: 2.4
Name: tree-sitter-language-version-15
Version: 0.25.0
Summary: Python bindings to the Tree-sitter parsing library. Temporary repo to get support for tree-sitter langange version 15
Author-email: Mark Hu <watermarkhu@gmail.com>
Project-URL: Source, https://github.com/watermarkhu/py-tree-sitter
Project-URL: Discord, https://discord.gg/w7nTvsVJhm
Project-URL: Matrix, https://matrix.to/#/#tree-sitter-chat:matrix.org
Keywords: incremental,parsing,tree-sitter
Classifier: Intended Audience :: Developers
Classifier: License :: OSI Approved :: MIT License
Classifier: Operating System :: OS Independent
Classifier: Programming Language :: C
Classifier: Programming Language :: Python
Classifier: Topic :: Software Development :: Compilers
Classifier: Topic :: Text Processing :: Linguistic
Classifier: Typing :: Typed
Requires-Python: >=3.10
License-File: LICENSE
Dynamic: license-file
